minimal_program_tester/__init__.py
minimal_program_tester/__main__.py
minimal_program_tester/minimal_program_tester.py
minimal_program_tester-0.0.3.dist-info/METADATA
minimal_program_tester-0.0.3.dist-info/WHEEL
minimal_program_tester-0.0.3.dist-info/top_level.txt
minimal_program_tester-0.0.3.dist-info/zip-safe
minimal_program_tester-0.0.3.dist-info/RECORD
