Metadata-Version: 2.1
Name: minimal_program_tester
Version: 0.0.3
Summary: A really minimalistic program tester
Author: Dewliak
Author-email: veres.z.benedek@gmail.com
Classifier: Programming Language :: Python :: 3
Classifier: License :: OSI Approved :: MIT License
Classifier: Operating System :: OS Independent
Requires-Python: >=3.10
Requires-Dist: colorama
